terminal_tutor/__init__.py
terminal_tutor/cli.py
terminal_tutor/core.py
terminal_tutor/installer.py
terminal_tutor/openai_manager.py
terminal_tutor/zsh_integration.zsh
terminal_tutor/data/commands.json
terminal_tutor-0.1.0.dist-info/licenses/LICENSE
terminal_tutor-0.1.0.dist-info/METADATA
terminal_tutor-0.1.0.dist-info/WHEEL
terminal_tutor-0.1.0.dist-info/entry_points.txt
terminal_tutor-0.1.0.dist-info/top_level.txt
terminal_tutor-0.1.0.dist-info/RECORD
