Metadata-Version: 2.4
Name: terminal-tutor
Version: 0.1.0
Summary: Real-time terminal command education for Zsh - 36-38ms predictions, 459+ commands (Zsh required)
Home-page: https://github.com/jatinmayekar/terminal-tutor
Author: Jatin Mayekar
Author-email: Jatin Mayekar <jatin@terminaltutor.dev>
License: Proprietary
Project-URL: Homepage, https://github.com/jatinmayekar/terminal-tutor
Keywords: terminal,cli,learning,commands,tutorial,zsh,shell,education,real-time
Classifier: Development Status :: 4 - Beta
Classifier: Intended Audience :: Developers
Classifier: License :: Other/Proprietary License
Classifier: Programming Language :: Python :: 3
Classifier: Programming Language :: Python :: 3.7
Classifier: Programming Language :: Python :: 3.8
Classifier: Programming Language :: Python :: 3.9
Classifier: Programming Language :: Python :: 3.10
Classifier: Programming Language :: Python :: 3.11
Classifier: Programming Language :: Python :: 3.12
Classifier: Programming Language :: Python :: 3.13
Classifier: Topic :: System :: Shells
Classifier: Topic :: Education
Requires-Python: >=3.7
License-File: LICENSE
Requires-Dist: rich>=10.0.0
Requires-Dist: requests>=2.25.0
Requires-Dist: openai>=1.0.0
Dynamic: author
Dynamic: home-page
Dynamic: license-file
Dynamic: requires-python
